<?xml version="1.0" encoding="iso-8859-15" ?>
<NewsML>
<NewsEnvelope>
	<DateAndTime>20250911T222610+0200</DateAndTime>
    <NewsService FormalName="Basic D SPI"/>
    <TransmissionID>17</TransmissionID>
</NewsEnvelope>

<NewsItem>
	<Identification>
		<NewsIdentifier>
			<ProviderId>awp.ch</ProviderId>
			<DateId>20250911</DateId>
			<NewsItemId>3633</NewsItemId>
			<RevisionId PreviousRevision="0" Update="N">1</RevisionId>
			<PublicIdentifier>urn:newsml:awp.ch:20250911:3633:1</PublicIdentifier>
		</NewsIdentifier>
	</Identification>

	<NewsManagement>
		<NewsItemType FormalName="News"/>
		<FirstCreated>20250911T222610+0200</FirstCreated>
		<ThisRevisionCreated>20250911T222610+0200</ThisRevisionCreated>
		<Status FormalName="Usable"/>
		<Urgency FormalName="4"/>
	</NewsManagement>

	<NewsComponent>

		<NewsLines>
			<HeadLine>Partners Group investiert in brasilianisches Softwareunternehmen Omie</HeadLine>
<NewsLine><NewsLineType FormalName="ByLine"/><NewsLineText></NewsLineText></NewsLine>

<NewsLine><NewsLineType FormalName="StoryType"/><NewsLineText></NewsLineText></NewsLine>

		</NewsLines>

		<AdministrativeMetadata>
			<Provider>
				<Party FormalName="AWP"/>
			</Provider>
			<Source>
				<Party FormalName="AWP"/>
			</Source>
		</AdministrativeMetadata>

		<DescriptiveMetadata>
			<Language FormalName="de"/>
			<Genre FormalName="Current"/>
			<SubjectCode><Subject FormalName="04016030"/><Subject FormalName="04016048"/><Subject FormalName="04006000"/></SubjectCode>
			<Location>
<!-- Country Structured -->
<Property FormalName="Country" Value="BR" />

<Property FormalName="Country" Value="CH">
<Property FormalName="City" Value="6341" />

</Property>


      </Location>

<!-- Company Relations -->
<Property FormalName="Company" Value="-2124422893">
<Property FormalName="FullName" Value="Partners Group Holding AG" />

<Property FormalName="ShortName" Value="Partners Group" />

<Property FormalName="Telekurs" Value="321079" />

<Property FormalName="CHNr" Value="CH-170.3.021.159-3" />

<Property FormalName="Instrument">
<Property FormalName="ISIN" Value="CH0024608827" />

<Property FormalName="Ticker" Value="PGHN" />

</Property>

<Property FormalName="Instrument">
<Property FormalName="ISIN" Value="CH0419041287" />

<Property FormalName="Ticker" Value="PAR191" />

</Property>

<Property FormalName="Instrument">
<Property FormalName="ISIN" Value="CH1293714346" />

<Property FormalName="Ticker" Value="PAR23" />

</Property>

<Property FormalName="Instrument">
<Property FormalName="ISIN" Value="CH1293714353" />

<Property FormalName="Ticker" Value="PAR231" />

</Property>

<Property FormalName="Instrument">
<Property FormalName="ISIN" Value="CH1346742930" />

<Property FormalName="Ticker" Value="PAR24" />

</Property>

<Property FormalName="Instrument">
<Property FormalName="ISIN" Value="CH1346742948" />

<Property FormalName="Ticker" Value="PAR241" />

</Property>

</Property>



<!-- relations -->
			<Property FormalName="Wire" Value="B"/><Property FormalName="Industry" Value="FIN"/><Property FormalName="Subject" Value="PRD"/><Property FormalName="Subject" Value="ERN"/>

		</DescriptiveMetadata>

		<ContentItem>
			<Format Scheme="IptcFormat" FormalName="NITF"/>
			<Characteristics>
				<Property FormalName="FormatVersion" Value="3.1"/>
			</Characteristics>
			<DataContent>
				<nitf>
					<body>
                    <body.content><p>Baar (awp) - Der Privatmarktspezialist Partners Group investiert im Namen seiner Kunden in den brasilianischen Softwareanbieter Omie. Das Zuger Finanzunternehmen werde im Rahmen der Finanzierungsrunde einen "bedeutenden Minderheitsanteil" an Omie übernehmen und Einsitz im Verwaltungsrat nehmen, um das zukünftige Wachstum des Unternehmens zu unterstützen, teilte Partners Group am Donnerstag mit.</p>
<p/><p>Die 2013 gegründete Omie ist laut den Angaben auf die Automatisierung von geschäftskritischen Geschäftsprozessen bei Kleinen und Mittleren Unternehmen (KMU) in Brasilien spezialisiert. Zudem biete es über Banking-as-a-Service-Partner eingebettete Finanzlösungen wie Cash Management, Zahlungsabwicklung und Kreditlösungen an. Insgesamt zählt das Unternehmen laut den Angaben rund 180'000 Kunden.</p>
<p/><p>Im Einklang mit seiner Investitionsstrategie werde Partners Group das Omie-Management bei der Umsetzung von strategischen Initiativen wie der beschleunigten Gewinnung von Neukunden oder der Steigerung der Rentabilität unterstützen, heisst es weiter. Über finanzielle Einzelheiten macht das Finanzinstitut keine Angaben.</p>
<p/><p>tp/</p>
</body.content>
					</body>
				</nitf>
			</DataContent>
		</ContentItem>

	</NewsComponent>

</NewsItem>


</NewsML>